tabutorch/__init__.py
tabutorch/nan/__init__.py
tabutorch/nan/policy.py
tabutorch/nan/reduction.py
tabutorch/preprocessing/__init__.py
tabutorch/preprocessing/base.py
tabutorch/preprocessing/standard_scaler.py
tabutorch/preprocessing/utils.py
tabutorch/testing/__init__.py
tabutorch/testing/fixtures.py
tabutorch/utils/__init__.py
tabutorch/utils/imports.py
tabutorch-0.0.1a0.dist-info/LICENSE
tabutorch-0.0.1a0.dist-info/METADATA
tabutorch-0.0.1a0.dist-info/WHEEL
tabutorch-0.0.1a0.dist-info/RECORD
