Metadata-Version: 2.1
Name: tabutorch
Version: 0.0.1a0
Summary: A light library to preprocess data with polars
Home-page: https://github.com/durandtibo/tabutorch
License: BSD-3-Clause
Keywords: ML,architecture,data,tabular,torch
Author: Thibaut Durand
Author-email: durand.tibo+gh@gmail.com
Requires-Python: >=3.9,<3.14
Classifier: Development Status :: 3 - Alpha
Classifier: Intended Audience :: Developers
Classifier: Intended Audience :: Information Technology
Classifier: Intended Audience :: Science/Research
Classifier: License :: OSI Approved :: BSD License
Classifier: Operating System :: POSIX :: Linux
Classifier: Programming Language :: Python :: 3
Classifier: Programming Language :: Python :: 3.9
Classifier: Programming Language :: Python :: 3.10
Classifier: Programming Language :: Python :: 3.11
Classifier: Programming Language :: Python :: 3.12
Classifier: Programming Language :: Python :: 3.13
Classifier: Topic :: Scientific/Engineering
Classifier: Topic :: Scientific/Engineering :: Artificial Intelligence
Classifier: Topic :: Software Development :: Libraries
Provides-Extra: all
Requires-Dist: coola (>=0.8.5,<1.0)
Requires-Dist: numpy (>=1.22,<2.0) ; (sys_platform == "darwin" and platform_machine != "arm64") and (extra == "all")
Requires-Dist: numpy (>=1.22,<3.0) ; extra == "all"
Requires-Dist: objectory (>=0.1,<1.0) ; extra == "all"
Requires-Dist: scikit-learn (>=1.0,<2.0) ; extra == "all"
Requires-Dist: torch (>=1.12,<2.3) ; sys_platform == "darwin" and platform_machine != "arm64"
Requires-Dist: torch (>=1.12,<3.0)
Project-URL: Repository, https://github.com/durandtibo/tabutorch
